[{"pk": 1, "model": "common.foto", "fields": {"nombre": "Vista1", "nombre_es": "Vista1", "imagen": "fotos/WlAzNCdklY6aqqnJXE0c.jpg", "nombre_en": null}}, {"pk": 2, "model": "common.foto", "fields": {"nombre": "Vista2", "nombre_es": "Vista2", "imagen": "fotos/KUGO5RWIL6g0iVbZBGQj.jpg", "nombre_en": null}}, {"pk": 3, "model": "common.foto", "fields": {"nombre": "Vsita3", "nombre_es": "Vsita3", "imagen": "fotos/htOOUPaLL1IRIphFh5P9.jpg", "nombre_en": null}}, {"pk": 4, "model": "common.foto", "fields": {"nombre": "Vista4", "nombre_es": "Vista4", "imagen": "fotos/ZQBmS8GgDPK9Y2Kq5VPM.jpg", "nombre_en": null}}, {"pk": 5, "model": "common.foto", "fields": {"nombre": "Vista1", "nombre_es": "Vista1", "imagen": "fotos/hYAqiNN3m9iaK5N3K7vP.jpg", "nombre_en": null}}, {"pk": 6, "model": "common.foto", "fields": {"nombre": "Vista2", "nombre_es": "Vista2", "imagen": "fotos/UglyvhJi5brMCcVpEPnL.jpg", "nombre_en": null}}, {"pk": 7, "model": "common.foto", "fields": {"nombre": "Vista3", "nombre_es": "Vista3", "imagen": "fotos/bimHL2lPe2TdX3AMP5oC.jpg", "nombre_en": null}}, {"pk": 8, "model": "common.foto", "fields": {"nombre": "Vista4", "nombre_es": "Vista4", "imagen": "fotos/U9j9JdYUP4hZatkKkUd7.jpg", "nombre_en": null}}, {"pk": 9, "model": "common.foto", "fields": {"nombre": "Vista1", "nombre_es": "Vista1", "imagen": "fotos/f4j4zCiTJungRuSCPgYD.jpg", "nombre_en": null}}, {"pk": 10, "model": "common.foto", "fields": {"nombre": "Vista2", "nombre_es": "Vista2", "imagen": "fotos/5u6LsooEfH1lEGPlu1sW.jpg", "nombre_en": null}}, {"pk": 11, "model": "common.foto", "fields": {"nombre": "Vista1", "nombre_es": "Vista1", "imagen": "fotos/BPWLaH1WCJWnMo95Tnvw.jpg", "nombre_en": null}}, {"pk": 12, "model": "common.foto", "fields": {"nombre": "Vista2", "nombre_es": "Vista2", "imagen": "fotos/6eiIgpVV3PfSNfG4e6cZ.jpg", "nombre_en": null}}, {"pk": 13, "model": "common.foto", "fields": {"nombre": "Vista1", "nombre_es": "Vista1", "imagen": "fotos/4clUPn6FrkqqPU2eFyzU.jpg", "nombre_en": null}}, {"pk": 14, "model": "common.foto", "fields": {"nombre": "Vista2", "nombre_es": "Vista2", "imagen": "fotos/l0l3s4OnyQsXZYKRsItZ.jpg", "nombre_en": null}}, {"pk": 15, "model": "common.foto", "fields": {"nombre": "Vista3", "nombre_es": "Vista3", "imagen": "fotos/SZVuKsqwk9M9WqS4YBUq.jpg", "nombre_en": null}}, {"pk": 16, "model": "common.foto", "fields": {"nombre": "Vista4", "nombre_es": "Vista4", "imagen": "fotos/x5QtpLNKPk1aioB4G40n.jpg", "nombre_en": null}}, {"pk": 17, "model": "common.foto", "fields": {"nombre": "Vista5", "nombre_es": "Vista5", "imagen": "fotos/l4rLdVO3QYJsFtzsukmS.jpg", "nombre_en": null}}, {"pk": 18, "model": "common.foto", "fields": {"nombre": "Vista6", "nombre_es": "Vista6", "imagen": "fotos/9PxhMZCKhzvbWTm180VW.jpg", "nombre_en": null}}, {"pk": 19, "model": "common.foto", "fields": {"nombre": "Vista1", "nombre_es": "Vista1", "imagen": "fotos/UyNbvuHuZRdwrG9ANbb4.jpg", "nombre_en": null}}, {"pk": 20, "model": "common.foto", "fields": {"nombre": "Vista2", "nombre_es": "Vista2", "imagen": "fotos/qsRYNTDWyf4UdRdbPsaT.jpg", "nombre_en": null}}, {"pk": 21, "model": "common.foto", "fields": {"nombre": "Vista3", "nombre_es": "Vista3", "imagen": "fotos/dLRtXWx2jRtuzUntNSWd.jpg", "nombre_en": null}}, {"pk": 22, "model": "common.foto", "fields": {"nombre": "Vista4", "nombre_es": "Vista4", "imagen": "fotos/LUOnN3fSCcCT0jHyjEnq.jpg", "nombre_en": null}}, {"pk": 23, "model": "common.foto", "fields": {"nombre": "Vista5", "nombre_es": "Vista5", "imagen": "fotos/UacINydd2ZENPIB9rdo4.jpg", "nombre_en": null}}, {"pk": 24, "model": "common.foto", "fields": {"nombre": "Vista6", "nombre_es": "Vista6", "imagen": "fotos/f6MPHOOJ4W0dXpybS3M5.jpg", "nombre_en": null}}, {"pk": 25, "model": "common.foto", "fields": {"nombre": "Vista7", "nombre_es": "Vista7", "imagen": "fotos/Fy5dwXunvPAZrccdFnbk.jpg", "nombre_en": null}}, {"pk": 26, "model": "common.foto", "fields": {"nombre": "Vista8", "nombre_es": "Vista8", "imagen": "fotos/YF3SORDE9XLC3Ymujhma.jpg", "nombre_en": null}}]